tf_inputs/__init__.py
tf_inputs/core.py
tf_inputs/text.py
tf_inputs-0.2.3.dist-info/LICENSE
tf_inputs-0.2.3.dist-info/METADATA
tf_inputs-0.2.3.dist-info/WHEEL
tf_inputs-0.2.3.dist-info/top_level.txt
tf_inputs-0.2.3.dist-info/RECORD
