Metadata-Version: 2.1
Name: tf-inputs
Version: 0.2.3
Summary: Input pipelines for TensorFlow that make sense.
Home-page: https://github.com/danielwatson6/tf-inputs.git
Author: Daniel Watson
Author-email: daniel.watson@nyu.edu
License: UNKNOWN
Platform: UNKNOWN
Classifier: Development Status :: 3 - Alpha
Classifier: Intended Audience :: Developers
Classifier: Programming Language :: Python :: 3.7
Classifier: License :: OSI Approved :: MIT License
